lolz/__init__.py
lolz/eh.py
lolz/types.py
lolz/sync/__init__.py
lolz/sync/core.py
lolz/sync/error.py
lolz/sync/request.py
lolz/sync/session.py
versus_lolz-0.1.2.dist-info/licenses/LICENSE.md
versus_lolz-0.1.2.dist-info/METADATA
versus_lolz-0.1.2.dist-info/WHEEL
versus_lolz-0.1.2.dist-info/top_level.txt
versus_lolz-0.1.2.dist-info/RECORD
