Metadata-Version: 2.4
Name: versus-lolz
Version: 0.1.2
Summary: Unofficial Python client for Lolzteam API
Home-page: https://github.com/Sema4ka0/versus.lolz
Author: Versus Team
Author-email: vi.is.chapmann@gmail.com
Classifier: Programming Language :: Python :: 3
Classifier: Operating System :: OS Independent
Requires-Python: >=3.10
License-File: LICENSE.md
Requires-Dist: colorama
Requires-Dist: aiohttp
Requires-Dist: requests
Dynamic: license-file
